fedot_ind/__init__.py
fedot_ind/api/__init__.py
fedot_ind/api/main.py
fedot_ind/api/utils/__init__.py
fedot_ind/api/utils/checkers_collections.py
fedot_ind/api/utils/data.py
fedot_ind/api/utils/industrial_strategy.py
fedot_ind/api/utils/metafeatures.py
fedot_ind/api/utils/path_lib.py
fedot_ind/api/utils/recurrent_image.py
fedot_ind/api/utils/saver_collections.py
fedot_ind/core/__init__.py
fedot_ind/core/architecture/__init__.py
fedot_ind/core/architecture/abstraction/__init__.py
fedot_ind/core/architecture/abstraction/decorators.py
fedot_ind/core/architecture/abstraction/сheckers.py
fedot_ind/core/architecture/pipelines/__init__.py
fedot_ind/core/architecture/pipelines/abstract_pipeline.py
fedot_ind/core/architecture/pipelines/anomaly_detection.py
fedot_ind/core/architecture/pipelines/classification.py
fedot_ind/core/architecture/postprocessing/__init__.py
fedot_ind/core/architecture/postprocessing/optimisation_history.py
fedot_ind/core/architecture/postprocessing/results_picker.py
fedot_ind/core/architecture/postprocessing/ucr_datasets.json
fedot_ind/core/architecture/postprocessing/visualisation/__init__.py
fedot_ind/core/architecture/postprocessing/visualisation/gradcam_vis.py
fedot_ind/core/architecture/preprocessing/__init__.py
fedot_ind/core/architecture/preprocessing/data_convertor.py
fedot_ind/core/architecture/settings/__init__.py
fedot_ind/core/architecture/settings/computational.py
fedot_ind/core/architecture/settings/pipeline_factory.py
fedot_ind/core/ensemble/__init__.py
fedot_ind/core/ensemble/base_ensembler.py
fedot_ind/core/ensemble/kernel_ensemble.py
fedot_ind/core/ensemble/random_automl_forest.py
fedot_ind/core/ensemble/rank_ensembler.py
fedot_ind/core/metrics/__init__.py
fedot_ind/core/metrics/evaluation.py
fedot_ind/core/metrics/loss/__init__.py
fedot_ind/core/metrics/loss/basis_loss.py
fedot_ind/core/metrics/loss/soft_dtw.py
fedot_ind/core/metrics/loss/svd_loss.py
fedot_ind/core/metrics/metrics_implementation.py
fedot_ind-0.4.2.dist-info/LICENSE.md
fedot_ind-0.4.2.dist-info/METADATA
fedot_ind-0.4.2.dist-info/WHEEL
fedot_ind-0.4.2.dist-info/RECORD
