Metadata-Version: 2.1
Name: fedot-ind
Version: 0.4.2
Summary: Time series analysis framework
License: BSD 3-Clause
Author: NSS Lab
Author-email: itmo.nss.team@gmail.com
Requires-Python: >=3.9,<3.12
Classifier: License :: Other/Proprietary License
Classifier: Programming Language :: Python :: 3
Classifier: Programming Language :: Python :: 3.9
Classifier: Programming Language :: Python :: 3.10
Classifier: Programming Language :: Python :: 3.11
Requires-Dist: PyMonad (==2.4.0)
Requires-Dist: PyWavelets (==1.4.1)
Requires-Dist: catboost (==1.1.1) ; sys_platform == "darwin"
Requires-Dist: chardet (>=5.2.0,<5.3.0)
Requires-Dist: datasets (>=2.18.0,<3.0.0)
Requires-Dist: datasetsforecast (>=0.0.8,<0.1.0)
Requires-Dist: distributed (>=2023.12.0,<2023.13.0)
Requires-Dist: fastai (>=2.7.14,<2.8.0)
Requires-Dist: fastcore (>=1.5.29,<1.6.0)
Requires-Dist: fedot (>=0.7.3.1,<0.8.0.0)
Requires-Dist: giotto_tda (==0.6.0)
Requires-Dist: librosa (>=0.10.1,<0.11.0)
Requires-Dist: matplotlib (>=3.8.2,<3.9.0)
Requires-Dist: mklpy (==0.6)
Requires-Dist: pillow (>=10.2.0,<10.3.0)
Requires-Dist: pyriemann (>=0.5,<0.6)
Requires-Dist: ripser (==0.6.4)
Requires-Dist: scipy (>=1.10.0)
Requires-Dist: seaborn (>=0.13.2,<0.14.0)
Requires-Dist: sktime (>=0.16.1)
Requires-Dist: statsforecast (==1.5.0)
Requires-Dist: tensorly (==0.8.1)
Requires-Dist: torch (>=2.2.0,<2.3.0)
Requires-Dist: torchvision (>=0.17.0,<0.18.0)
Requires-Dist: tqdm (>=4.65.2,<4.66.0)
